devana/__init__.py
devana/_version.py
devana/configuration.py
devana/code_generation/__init__.py
devana/code_generation/stubtype.py
devana/code_generation/printers/__init__.py
devana/code_generation/printers/codeprinter.py
devana/code_generation/printers/configuration.py
devana/code_generation/printers/dispatcherinjectable.py
devana/code_generation/printers/formatter.py
devana/code_generation/printers/icodeprinter.py
devana/code_generation/printers/default/__init__.py
devana/code_generation/printers/default/attributeprinter.py
devana/code_generation/printers/default/basictypeprinter.py
devana/code_generation/printers/default/classprinter.py
devana/code_generation/printers/default/commentprinter.py
devana/code_generation/printers/default/conceptprinter.py
devana/code_generation/printers/default/defaultprinter.py
devana/code_generation/printers/default/enumprinter.py
devana/code_generation/printers/default/externcprinter.py
devana/code_generation/printers/default/fileprinter.py
devana/code_generation/printers/default/functionprinter.py
devana/code_generation/printers/default/functiontypeprinter.py
devana/code_generation/printers/default/namespaceprinter.py
devana/code_generation/printers/default/stubtypeprinter.py
devana/code_generation/printers/default/templateparameterprinter.py
devana/code_generation/printers/default/typedefprinter.py
devana/code_generation/printers/default/typeexpressionprinter.py
devana/code_generation/printers/default/unionprinter.py
devana/code_generation/printers/default/usingnamespaceprinter.py
devana/code_generation/printers/default/usingprinter.py
devana/code_generation/printers/default/utilityprinters.py
devana/code_generation/printers/default/variableprinter.py
devana/libcxx/include/CMakeLists.txt
devana/libcxx/include/__assert
devana/libcxx/include/__availability
devana/libcxx/include/__bit_reference
devana/libcxx/include/__bits
devana/libcxx/include/__bsd_locale_defaults.h
devana/libcxx/include/__bsd_locale_fallbacks.h
devana-2.4.0.dist-info/licenses/LICENSE
devana-2.4.0.dist-info/METADATA
devana-2.4.0.dist-info/WHEEL
devana-2.4.0.dist-info/top_level.txt
devana-2.4.0.dist-info/RECORD
