Metadata-Version: 2.4
Name: devana
Version: 2.4.0
Summary: Python package to parse and generate C/C++ code as context aware preprocessor.
Home-page: https://github.com/JhnW/devana
Author: JhnW
Author-email: jhnw.global@gmail.com
License: LGPLv2+
Project-URL: Source, https://github.com/JhnW/devana
Project-URL: Bug Tracker, https://github.com/JhnW/devana/issues
Project-URL: Documentation, http://jhnw.github.io/devana
Keywords: C++,development,parser,generator
Classifier: Development Status :: 4 - Beta
Classifier: Intended Audience :: Developers
Classifier: Topic :: Software Development :: Code Generators
Classifier: Topic :: Software Development :: Build Tools
Classifier: Topic :: Software Development :: Compilers
Classifier: Operating System :: Microsoft :: Windows
Classifier: Operating System :: POSIX
Classifier: Operating System :: MacOS
Classifier: Programming Language :: Python :: 3.8
Classifier: Programming Language :: Python :: 3.9
Classifier: Programming Language :: Python :: 3.10
Classifier: Programming Language :: Python :: 3.11
Classifier: Programming Language :: Python :: 3.12
Classifier: License :: OSI Approved :: GNU Lesser General Public License v2 or later (LGPLv2+)
Requires-Python: >=3.8
License-File: LICENSE
Requires-Dist: libclang==18.1.1
Dynamic: license-file
